eric_mcp_server/__init__.py
eric_mcp_server/__main__.py
eric_mcp_server/my_mcp_server.py
eric_mcp_server-1.0.0.dist-info/METADATA
eric_mcp_server-1.0.0.dist-info/WHEEL
eric_mcp_server-1.0.0.dist-info/entry_points.txt
eric_mcp_server-1.0.0.dist-info/RECORD
