Metadata-Version: 2.4
Name: eric-mcp-server
Version: 1.0.0
Summary: FinICR智能文档处理MCP服务
Requires-Python: >=3.10
Requires-Dist: fastmcp
Requires-Dist: requests
Requires-Dist: twine>=6.2.0
